{"nm":"Getting Information","mn":"","layers":[{"ty":4,"nm":"Getting Information 1 Outlines","mn":"","sr":1,"st":0,"op":150,"ip":0,"hd":false,"cl":"","ln":"","ddd":0,"bm":0,"hasMask":false,"ao":0,"ks":{"a":{"a":0,"k":[64.576,50.431,0]},"s":{"a":0,"k":[1098,1098,100]},"sk":{"a":0,"k":0},"p":{"a":1,"k":[{"o":{"x":0.333,"y":0},"i":{"x":0.667,"y":1},"s":[772.003,713.67,0],"t":0},{"o":{"x":0.333,"y":0.333},"i":{"x":0.667,"y":0.667},"s":[382.003,415.67,0],"t":30},{"o":{"x":0.333,"y":0},"i":{"x":0.667,"y":1},"s":[382.003,415.67,0],"t":35},{"o":{"x":0.333,"y":0.333},"i":{"x":0.667,"y":0.667},"s":[486.003,594.67,0],"t":55},{"o":{"x":0.333,"y":0},"i":{"x":0.667,"y":1},"s":[486.003,594.67,0],"t":60},{"o":{"x":0.333,"y":0.333},"i":{"x":0.667,"y":0.667},"s":[666.003,412.67,0],"t":85},{"o":{"x":0.333,"y":0},"i":{"x":0.667,"y":1},"s":[666.003,412.67,0],"t":90},{"o":{"x":0.167,"y":0.167},"i":{"x":0.833,"y":0.833},"s":[772.003,713.67,0],"t":130}]},"sa":{"a":0,"k":0},"o":{"a":0,"k":100},"r":{"a":0,"k":0}},"ef":[],"shapes":[{"ty":"gr","bm":0,"cl":"","ln":"","hd":false,"mn":"","nm":"Group 1","np":0,"it":[{"ty":"sh","bm":0,"cl":"","ln":"","hd":false,"mn":"","nm":"Path 1","d":1,"ks":{"a":0,"k":{"c":true,"i":[[0,-5.883],[5.883,0],[0,5.883],[-5.883,0]],"o":[[0,5.883],[-5.883,0],[0,-5.883],[5.883,0]],"v":[[10.671,0.001],[0,10.671],[-10.671,0.001],[0,-10.671]]}}},{"ty":"mm","bm":0,"cl":"","ln":"","hd":false,"mn":"","nm":"Merge Paths 1","mm":4},{"ty":"fl","bm":0,"cl":"","ln":"","hd":false,"mn":"","nm":"Fill 1","c":{"a":0,"k":[0.9804,0.8745,0.4392]},"r":1,"o":{"a":0,"k":20}},{"ty":"tr","a":{"a":0,"k":[0,0]},"s":{"a":0,"k":[100,100]},"sk":{"a":0,"k":0},"p":{"a":0,"k":[64.022,50.651]},"r":{"a":0,"k":0},"sa":{"a":0,"k":0},"o":{"a":0,"k":100}}]},{"ty":"gr","bm":0,"cl":"","ln":"","hd":false,"mn":"","nm":"Group 2","np":0,"it":[{"ty":"sh","bm":0,"cl":"","ln":"","hd":false,"mn":"","nm":"Path 1","d":1,"ks":{"a":0,"k":{"c":true,"i":[[5.883,0],[0,5.883],[-5.883,0],[0,-5.883]],"o":[[-5.883,0],[0,-5.883],[5.883,0],[0,5.883]],"v":[[-2.609,7.891],[-13.281,-2.779],[-2.609,-13.451],[8.062,-2.779]]}}},{"ty":"sh","bm":0,"cl":"","ln":"","hd":false,"mn":"","nm":"Path 2","d":1,"ks":{"a":0,"k":{"c":true,"i":[[0.449,0.449],[0,0],[0,3.278],[7.156,0],[0,-7.156],[-7.156,0],[-2.218,1.768],[0,0],[-0.294,0],[-0.225,0.225]],"o":[[0,0],[2.017,-2.288],[0,-7.156],[-7.156,0],[0,7.155],[3.048,0],[0,0],[0.225,0.225],[0.294,0],[0.449,-0.449]],"v":[[15.137,13.786],[7.128,5.783],[10.367,-2.779],[-2.609,-15.756],[-15.585,-2.779],[-2.609,10.195],[5.463,7.368],[13.506,15.415],[14.325,15.756],[15.137,15.415]]}}},{"ty":"mm","bm":0,"cl":"","ln":"","hd":false,"mn":"","nm":"Merge Paths 1","mm":1},{"ty":"mm","bm":0,"cl":"","ln":"","hd":false,"mn":"","nm":"Merge Paths 2","mm":4},{"ty":"fl","bm":0,"cl":"","ln":"","hd":false,"mn":"","nm":"Fill 1","c":{"a":0,"k":[0.9804,0.8745,0.4392]},"r":1,"o":{"a":0,"k":100}},{"ty":"tr","a":{"a":0,"k":[0,0]},"s":{"a":0,"k":[100,100]},"sk":{"a":0,"k":0},"p":{"a":0,"k":[66.632,53.431]},"r":{"a":0,"k":0},"sa":{"a":0,"k":0},"o":{"a":0,"k":100}}]}],"ind":1},{"ty":4,"nm":"Getting Information 2 Outlines","mn":"","sr":1,"st":0,"op":150,"ip":0,"hd":false,"cl":"","ln":"","ddd":0,"bm":0,"hasMask":false,"ao":0,"ks":{"a":{"a":0,"k":[50,50,0]},"s":{"a":0,"k":[1098,1098,100]},"sk":{"a":0,"k":0},"p":{"a":0,"k":[512,512,0]},"sa":{"a":0,"k":0},"o":{"a":0,"k":100},"r":{"a":0,"k":0}},"ef":[],"shapes":[{"ty":"gr","bm":0,"cl":"","ln":"","hd":false,"mn":"","nm":"Group 1","np":0,"it":[{"ty":"sh","bm":0,"cl":"","ln":"","hd":false,"mn":"","nm":"Path 1","d":1,"ks":{"a":0,"k":{"c":true,"i":[[0.008,-0.275],[0.261,0.021],[3.074,-0.822],[0.042,0],[0.061,0.224],[-0.268,0.072],[-0.54,-0.017]],"o":[[-0.01,0.276],[-0.131,-0.004],[-0.043,0.011],[-0.221,0],[-0.071,-0.266],[3.213,-0.86],[0.276,0.009]],"v":[[20.485,3.821],[19.97,4.306],[3.755,4.744],[3.626,4.76],[3.142,4.389],[3.497,3.777],[20,3.306]]}}},{"ty":"sh","bm":0,"cl":"","ln":"","hd":false,"mn":"","nm":"Path 2","d":1,"ks":{"a":0,"k":{"c":true,"i":[[0.008,-0.275],[0.261,-0.02],[3.073,-0.824],[0.043,0],[0.061,0.222],[-0.267,0.073],[-0.539,-0.016]],"o":[[-0.01,0.277],[-0.131,-0.004],[-0.044,0.011],[-0.221,0],[-0.071,-0.268],[3.217,-0.861],[0.276,0.009]],"v":[[20.485,-1.737],[19.97,-1.251],[3.756,-0.813],[3.626,-0.796],[3.142,-1.166],[3.496,-1.78],[20,-2.251]]}}},{"ty":"sh","bm":0,"cl":"","ln":"","hd":false,"mn":"","nm":"Path 3","d":1,"ks":{"a":0,"k":{"c":true,"i":[[0.008,-0.276],[0.261,-0.007],[3.072,-0.826],[0.043,0],[0.061,0.223],[-0.267,0.072],[-0.541,-0.017]],"o":[[-0.01,0.276],[-0.131,-0.004],[-0.044,0.01],[-0.221,0],[-0.071,-0.268],[3.216,-0.861],[0.276,0.009]],"v":[[20.485,-7.293],[19.97,-6.808],[3.756,-6.37],[3.626,-6.354],[3.142,-6.724],[3.496,-7.337],[20,-7.808]]}}},{"ty":"sh","bm":0,"cl":"","ln":"","hd":false,"mn":"","nm":"Path 4","d":1,"ks":{"a":0,"k":{"c":true,"i":[[-0.268,0.072],[-0.54,-0.017],[0.008,-0.275],[0.261,0.008],[3.074,-0.822],[0.042,0],[0.061,0.224]],"o":[[3.213,-0.859],[0.276,0.009],[-0.01,0.276],[-0.131,-0.003],[-0.043,0.011],[-0.221,0],[-0.071,-0.266]],"v":[[3.497,-12.895],[20,-13.366],[20.485,-12.851],[19.97,-12.366],[3.755,-11.928],[3.626,-11.911],[3.142,-12.283]]}}},{"ty":"sh","bm":0,"cl":"","ln":"","hd":false,"mn":"","nm":"Path 5","d":1,"ks":{"a":0,"k":{"c":true,"i":[[0.071,-0.266],[0.22,0],[0.043,0.011],[0.132,-0.004],[0.009,0.276],[-0.277,0.009],[-3.215,-0.86]],"o":[[-0.061,0.224],[-0.042,0],[-3.075,-0.822],[-0.256,0.02],[-0.008,-0.275],[0.538,-0.017],[0.268,0.072]],"v":[[-2.805,4.389],[-3.288,4.76],[-3.417,4.744],[-19.633,4.306],[-20.148,3.821],[-19.662,3.306],[-3.16,3.777]]}}},{"ty":"sh","bm":0,"cl":"","ln":"","hd":false,"mn":"","nm":"Path 6","d":1,"ks":{"a":0,"k":{"c":true,"i":[[0.071,-0.268],[0.22,0],[0.044,0.011],[0.133,-0.004],[0.009,0.277],[-0.277,0.009],[-3.215,-0.86]],"o":[[-0.061,0.222],[-0.043,0],[-3.074,-0.823],[-0.256,-0.021],[-0.008,-0.275],[0.541,-0.017],[0.267,0.073]],"v":[[-2.805,-1.166],[-3.288,-0.796],[-3.418,-0.813],[-19.633,-1.251],[-20.148,-1.737],[-19.662,-2.251],[-3.159,-1.78]]}}},{"ty":"sh","bm":0,"cl":"","ln":"","hd":false,"mn":"","nm":"Path 7","d":1,"ks":{"a":0,"k":{"c":true,"i":[[0.071,-0.268],[0.22,0],[0.044,0.01],[0.132,-0.004],[0.009,0.276],[-0.277,0.009],[-3.216,-0.861]],"o":[[-0.061,0.223],[-0.043,0],[-3.076,-0.826],[-0.256,-0.007],[-0.008,-0.276],[0.54,-0.016],[0.267,0.072]],"v":[[-2.805,-6.724],[-3.288,-6.354],[-3.418,-6.37],[-19.633,-6.808],[-20.148,-7.293],[-19.662,-7.808],[-3.159,-7.337]]}}},{"ty":"sh","bm":0,"cl":"","ln":"","hd":false,"mn":"","nm":"Path 8","d":1,"ks":{"a":0,"k":{"c":true,"i":[[0.071,-0.266],[0.22,0],[0.043,0.011],[0.132,-0.003],[0.009,0.276],[-0.277,0.009],[-3.215,-0.859]],"o":[[-0.061,0.224],[-0.042,0],[-3.075,-0.823],[-0.256,0.007],[-0.008,-0.275],[0.538,-0.017],[0.268,0.072]],"v":[[-2.805,-12.283],[-3.288,-11.911],[-3.417,-11.928],[-19.633,-12.366],[-20.148,-12.851],[-19.662,-13.366],[-3.16,-12.895]]}}},{"ty":"sh","bm":0,"cl":"","ln":"","hd":false,"mn":"","nm":"Path 9","d":1,"ks":{"a":0,"k":{"c":true,"i":[[0,0],[4.012,-6.439],[4.859,0],[1.638,-0.334],[0,0],[0,0],[-0.008,-0.097],[0,0],[-4.388,0],[0,0]],"o":[[-3.336,-0.68],[-2.047,-3.276],[-4.689,0],[0,0],[0,0],[4.391,0],[0,0],[0.006,-0.101],[0,0],[0,0]],"v":[[22.795,15.047],[0.005,18.05],[-11.902,13.878],[-22.786,15.047],[-22.786,-23.145],[-5.116,-23.145],[-0.494,-20.659],[0.504,-20.656],[5.115,-23.145],[22.795,-23.145]]}}},{"ty":"sh","bm":0,"cl":"","ln":"","hd":false,"mn":"","nm":"Path 10","d":1,"ks":{"a":0,"k":{"c":true,"i":[[0,0],[0,0],[0,0],[0.627,-0.959],[3.13,0],[0,0],[0,0],[0,0],[0,0],[0,0],[-2.88,-4.56],[0,0],[0,0],[0,0]],"o":[[0,0],[0,0],[-3.08,0],[-0.615,-0.959],[0,0],[0,0],[0,0],[0,0],[0,0],[0,0],[2.87,-4.56],[0,0],[0,0],[0,0]],"v":[[23.795,-19.195],[23.795,-24.145],[5.115,-24.145],[0.016,-22.073],[-5.116,-24.145],[-23.786,-24.145],[-23.786,-19.195],[-27.745,-19.195],[-27.745,19.145],[-10.455,19.145],[0.005,24.145],[10.455,19.145],[27.745,19.145],[27.745,-19.195]]}}},{"ty":"mm","bm":0,"cl":"","ln":"","hd":false,"mn":"","nm":"Merge Paths 1","mm":1},{"ty":"mm","bm":0,"cl":"","ln":"","hd":false,"mn":"","nm":"Merge Paths 2","mm":4},{"ty":"fl","bm":0,"cl":"","ln":"","hd":false,"mn":"","nm":"Fill 1","c":{"a":0,"k":[1,1,1]},"r":1,"o":{"a":0,"k":100}},{"ty":"tr","a":{"a":0,"k":[0,0]},"s":{"a":0,"k":[100,100]},"sk":{"a":0,"k":0},"p":{"a":0,"k":[51.507,53.181]},"r":{"a":0,"k":0},"sa":{"a":0,"k":0},"o":{"a":0,"k":100}}]}],"ind":2}],"ddd":0,"h":1024,"w":1024,"meta":{"a":"","k":"","d":"","g":"@lottiefiles/toolkit-js 0.21.3","tc":"#000000"},"v":"5.7.1","fr":30,"op":140,"ip":0,"assets":[]}